git_pretty
