Metadata-Version: 1.1
Name: git-pretty
Version: 0.1.2
Summary: An implementation of Justin Hileman's chart from "Changing History, or How to Git Pretty"
Home-page: https://github.com/draperunner/git-pretty
Author: Mats Byrkjeland
Author-email: matsbyr@gmail.com
License: MIT
Keywords: git
Platform: UNKNOWN
Classifier: Development Status :: 4 - Beta
Classifier: Intended Audience :: Developers
Classifier: Topic :: Software Development
Classifier: Topic :: Software Development :: Version Control :: Git
Classifier: License :: OSI Approved :: MIT License
Classifier: Programming Language :: Python :: 2.7
Classifier: Programming Language :: Python :: 3
Classifier: Programming Language :: Python :: 3.3
Classifier: Programming Language :: Python :: 3.4
Classifier: Programming Language :: Python :: 3.5
